{"1": {"label": "1", "d1": 204, "d2": 855.22, "d3": 0.00333, "output": 126476.49023}, "2": {"label": "1", "d1": 264, "d2": 535.13, "d3": 0.0025, "output": 103327.78017}, "3": {"label": "1", "d1": 96, "d2": 148.07, "d3": 0.0075, "output": 10107.027}, "4": {"label": "1", "d1": 60, "d2": 843.39, "d3": 0.00417, "output": 44687.4921}, "5": {"label": "1", "d1": 48, "d2": 281.95, "d3": 0.00667, "output": 11548.32315}, "6": {"label": "1", "d1": 252, "d2": 663.21, "d3": 0.00667, "output": 80812.22447}, "7": {"label": "1", "d1": 24, "d2": 936.41, "d3": 0.00083, "output": 22242.3418}, "8": {"label": "1", "d1": 192, "d2": 210.94, "d3": 0.00167, "output": 34624.65776}, "9": {"label": "1", "d1": 132, "d2": 104.77, "d3": 0.00167, "output": 12402.17891}, "10": {"label": "1", "d1": 36, "d2": 263.05, "d3": 0.00583, "output": 8519.76409}, "11": {"label": "1", "d1": 132, "d2": 201.99, "d3": 0.0075, "output": 16887.6608}, "12": {"label": "1", "d1": 36, "d2": 510.07, "d3": 0.0075, "output": 16040.07195}, "13": {"label": "1", "d1": 72, "d2": 757.51, "d3": 0.00667, "output": 43199.40856}, "14": {"label": "1", "d1": 96, "d2": 660.25, "d3": 0.00583, "output": 48434.80357}, "15": {"label": "1", "d1": 168, "d2": 678.35, "d3": 0.0075, "output": 64670.20169}, "16": {"label": "1", "d1": 156, "d2": 145.77, "d3": 0.005, "output": 15763.63191}, "17": {"label": "1", "d1": 156, "d2": 347.36, "d3": 0.0025, "output": 44825.2142}, "18": {"label": "1", "d1": 300, "d2": 838.94, "d3": 0.00083, "output": 222712.80454}, "19": {"label": "1", "d1": 324, "d2": 702.83, "d3": 0.0025, "output": 155941.68173}, "20": {"label": "1", "d1": 324, "d2": 628.66, "d3": 0.00167, "output": 157209.42279}, "21": {"label": "1", "d1": 180, "d2": 986.97, "d3": 0.0075, "output": 97308.73672}, "22": {"label": "1", "d1": 252, "d2": 688.39, "d3": 0.0075, "output": 77821.02349}, "23": {"label": "1", "d1": 72, "d2": 717.75, "d3": 0.00417, "output": 44561.9569}, "24": {"label": "1", "d1": 48, "d2": 299.8, "d3": 0.00583, "output": 12520.67869}, "25": {"label": "1", "d1": 252, "d2": 990.85, "d3": 0.0075, "output": 112013.48236}, "26": {"label": "1", "d1": 300, "d2": 878.84, "d3": 0.0025, "output": 185326.66225}, "27": {"label": "1", "d1": 348, "d2": 698.09, "d3": 0.0025, "output": 162122.5652}, "28": {"label": "1", "d1": 120, "d2": 331.72, "d3": 0.00667, "output": 27336.09129}, "29": {"label": "1", "d1": 132, "d2": 401.77, "d3": 0.005, "output": 38754.57298}, "30": {"label": "1", "d1": 252, "d2": 547.24, "d3": 0.00667, "output": 66681.26494}, "31": {"label": "1", "d1": 60, "d2": 311.77, "d3": 0.00667, "output": 15374.55638}, "32": {"label": "1", "d1": 48, "d2": 105.56, "d3": 0.00167, "output": 4865.21801}, "33": {"label": "1", "d1": 324, "d2": 276.86, "d3": 0.00667, "output": 36692.03537}, "34": {"label": "1", "d1": 216, "d2": 268.1, "d3": 0.00667, "output": 30632.83736}, "35": {"label": "1", "d1": 324, "d2": 757.37, "d3": 0.00417, "output": 134457.88935}, "36": {"label": "1", "d1": 192, "d2": 988.05, "d3": 0.005, "output": 121765.3309}, "37": {"label": "1", "d1": 72, "d2": 408.45, "d3": 0.0075, "output": 22659.51889}, "38": {"label": "1", "d1": 36, "d2": 594.96, "d3": 0.005, "output": 19556.93982}, "39": {"label": "1", "d1": 96, "d2": 404.9, "d3": 0.00167, "output": 35886.97436}, "40": {"label": "1", "d1": 204, "d2": 686.26, "d3": 0.00417, "output": 94154.12577}, "41": {"label": "1", "d1": 96, "d2": 324.04, "d3": 0.00667, "output": 22918.6358}, "42": {"label": "1", "d1": 228, "d2": 153.09, "d3": 0.00417, "output": 22496.81735}, "43": {"label": "1", "d1": 312, "d2": 329.83, "d3": 0.00083, "output": 90629.01637}, "44": {"label": "1", "d1": 96, "d2": 155.98, "d3": 0.0075, "output": 10646.95125}, "45": {"label": "1", "d1": 72, "d2": 938.14, "d3": 0.00083, "output": 65541.02241}, "46": {"label": "1", "d1": 180, "d2": 625.5, "d3": 0.0025, "output": 90575.8224}, "47": {"label": "1", "d1": 180, "d2": 451.01, "d3": 0.005, "output": 53446.27015}, "48": {"label": "1", "d1": 72, "d2": 809.95, "d3": 0.00083, "output": 56585.31893}, "49": {"label": "1", "d1": 132, "d2": 186.34, "d3": 0.00083, "output": 23288.20821}, "50": {"label": "1", "d1": 132, "d2": 206.97, "d3": 0.00167, "output": 24500.13332}, "51": {"label": "1", "d1": 12, "d2": 221.32, "d3": 0.00083, "output": 2641.56707}, "52": {"label": "1", "d1": 156, "d2": 696.2, "d3": 0.00333, "output": 84601.18912}, "53": {"label": "1", "d1": 108, "d2": 559.69, "d3": 0.00667, "output": 42984.34048}, "54": {"label": "1", "d1": 204, "d2": 631.82, "d3": 0.0075, "output": 65896.68632}, "55": {"label": "1", "d1": 324, "d2": 650.1, "d3": 0.00167, "output": 162570.9378}, "56": {"label": "1", "d1": 336, "d2": 868.29, "d3": 0.005, "output": 141156.90113}, "57": {"label": "1", "d1": 300, "d2": 922.93, "d3": 0.00333, "output": 174924.56516}, "58": {"label": "1", "d1": 264, "d2": 245.48, "d3": 0.0075, "output": 28178.05737}, "59": {"label": "1", "d1": 48, "d2": 866.24, "d3": 0.00083, "output": 40745.5741}, "60": {"label": "1", "d1": 192, "d2": 210.2, "d3": 0.0075, "output": 21350.59601}, "61": {"label": "1", "d1": 192, "d2": 641.45, "d3": 0.00083, "output": 113802.73712}, "62": {"label": "1", "d1": 348, "d2": 521.92, "d3": 0.00667, "output": 70508.56913}, "63": {"label": "1", "d1": 132, "d2": 299.61, "d3": 0.0025, "output": 33649.81544}, "64": {"label": "1", "d1": 312, "d2": 666.06, "d3": 0.0025, "output": 144174.69995}, "65": {"label": "1", "d1": 312, "d2": 414.9, "d3": 0.00583, "output": 59562.46886}, "66": {"label": "1", "d1": 156, "d2": 754.25, "d3": 0.0025, "output": 97332.50175}, "67": {"label": "1", "d1": 108, "d2": 652.23, "d3": 0.00417, "output": 56621.10526}, "68": {"label": "1", "d1": 228, "d2": 553.67, "d3": 0.0025, "output": 96133.09128}, "69": {"label": "1", "d1": 336, "d2": 968.95, "d3": 0.00417, "output": 174959.47496}, "70": {"label": "1", "d1": 264, "d2": 360.41, "d3": 0.0075, "output": 41370.59499}, "71": {"label": "1", "d1": 24, "d2": 303.05, "d3": 0.00667, "output": 6700.32997}, "72": {"label": "1", "d1": 96, "d2": 670.26, "d3": 0.00333, "output": 54996.07746}, "73": {"label": "1", "d1": 108, "d2": 156.8, "d3": 0.00167, "output": 15483.27846}, "74": {"label": "1", "d1": 36, "d2": 460.05, "d3": 0.00417, "output": 15348.97112}, "75": {"label": "1", "d1": 276, "d2": 589.98, "d3": 0.0075, "output": 68660.75518}, "76": {"label": "1", "d1": 204, "d2": 989.94, "d3": 0.00083, "output": 185705.59276}, "77": {"label": "1", "d1": 12, "d2": 957.77, "d3": 0.00083, "output": 11431.47339}, "78": {"label": "1", "d1": 144, "d2": 572.63, "d3": 0.0075, "output": 50317.62338}, "79": {"label": "1", "d1": 60, "d2": 820.68, "d3": 0.00583, "output": 41449.92641}, "80": {"label": "1", "d1": 348, "d2": 602.72, "d3": 0.0025, "output": 139974.09002}, "81": {"label": "1", "d1": 324, "d2": 401.44, "d3": 0.00083, "output": 114004.30052}, "82": {"label": "1", "d1": 84, "d2": 727.63, "d3": 0.00667, "output": 46678.23468}, "83": {"label": "1", "d1": 96, "d2": 748.75, "d3": 0.0025, "output": 63834.38411}, "84": {"label": "1", "d1": 192, "d2": 116.47, "d3": 0.00083, "output": 20663.50424}, "85": {"label": "1", "d1": 336, "d2": 567.01, "d3": 0.00083, "output": 166196.62977}, "86": {"label": "1", "d1": 96, "d2": 280.41, "d3": 0.00333, "output": 23008.16113}, "87": {"label": "1", "d1": 96, "d2": 314.75, "d3": 0.00417, "output": 24858.18698}, "88": {"label": "1", "d1": 132, "d2": 425.98, "d3": 0.0025, "output": 47842.69011}, "89": {"label": "1", "d1": 84, "d2": 547.88, "d3": 0.00167, "output": 42906.37097}, "90": {"label": "1", "d1": 252, "d2": 360.19, "d3": 0.00083, "output": 81873.44106}, "91": {"label": "1", "d1": 180, "d2": 194.37, "d3": 0.00083, "output": 32486.03579}, "92": {"label": "1", "d1": 120, "d2": 996.19, "d3": 0.00583, "output": 85813.44846}, "93": {"label": "1", "d1": 12, "d2": 270.56, "d3": 0.00167, "output": 3211.74981}, "94": {"label": "1", "d1": 216, "d2": 564.14, "d3": 0.00333, "output": 86791.96407}, "95": {"label": "1", "d1": 168, "d2": 652.5, "d3": 0.00083, "output": 102280.93013}, "96": {"label": "1", "d1": 12, "d2": 778.74, "d3": 0.00583, "output": 9000.18354}, "97": {"label": "1", "d1": 48, "d2": 346.6, "d3": 0.00167, "output": 15974.65483}, "98": {"label": "1", "d1": 216, "d2": 368.9, "d3": 0.00417, "output": 52456.46338}, "99": {"label": "1", "d1": 276, "d2": 862.84, "d3": 0.00083, "output": 212757.13702}, "100": {"label": "1", "d1": 276, "d2": 223.54, "d3": 0.0075, "output": 26015.16189}, "101": {"label": "3", "d1": 87600, "d2": 180, "d3": 0.00083, "output": 524.12711}, "102": {"label": "3", "d1": 72300, "d2": 108, "d3": 0.0075, "output": 979.1523}, "103": {"label": "3", "d1": 22100, "d2": 108, "d3": 0.0075, "output": 299.29828}, "104": {"label": "3", "d1": 18200, "d2": 288, "d3": 0.00083, "output": 71.07417}, "105": {"label": "3", "d1": 82400, "d2": 228, "d3": 0.00417, "output": 560.72892}, "106": {"label": "3", "d1": 20800, "d2": 276, "d3": 0.0075, "output": 178.72777}, "107": {"label": "3", "d1": 82300, "d2": 264, "d3": 0.0025, "output": 426.22806}, "108": {"label": "3", "d1": 62500, "d2": 288, "d3": 0.00083, "output": 244.07338}, "109": {"label": "3", "d1": 97200, "d2": 204, "d3": 0.0075, "output": 931.95739}, "110": {"label": "3", "d1": 49500, "d2": 36, "d3": 0.00583, "output": 1528.32577}, "111": {"label": "3", "d1": 12400, "d2": 228, "d3": 0.00333, "output": 77.70603}, "112": {"label": "3", "d1": 63000, "d2": 60, "d3": 0.00083, "output": 1076.79759}, "113": {"label": "3", "d1": 49000, "d2": 300, "d3": 0.00417, "output": 286.56333}, "114": {"label": "3", "d1": 78400, "d2": 204, "d3": 0.0075, "output": 751.70226}, "115": {"label": "3", "d1": 26500, "d2": 312, "d3": 0.00333, "output": 136.69394}, "116": {"label": "3", "d1": 14000, "d2": 204, "d3": 0.00583, "output": 117.52024}, "117": {"label": "3", "d1": 8200, "d2": 276, "d3": 0.00583, "output": 59.83293}, "118": {"label": "3", "d1": 23100, "d2": 228, "d3": 0.0075, "output": 211.80316}, "119": {"label": "3", "d1": 64600, "d2": 324, "d3": 0.0075, "output": 531.73901}, "120": {"label": "3", "d1": 88900, "d2": 204, "d3": 0.0025, "output": 556.84711}, "121": {"label": "3", "d1": 56700, "d2": 156, "d3": 0.0025, "output": 439.38021}, "122": {"label": "3", "d1": 32200, "d2": 240, "d3": 0.00667, "output": 269.41387}, "123": {"label": "3", "d1": 65300, "d2": 204, "d3": 0.005, "output": 511.3648}, "124": {"label": "3", "d1": 44900, "d2": 276, "d3": 0.00583, "output": 327.62179}, "125": {"label": "3", "d1": 36100, "d2": 204, "d3": 0.00333, "output": 244.1042}, "126": {"label": "3", "d1": 98000, "d2": 168, "d3": 0.005, "output": 863.61121}, "127": {"label": "3", "d1": 21000, "d2": 324, "d3": 0.0025, "output": 94.64711}, "128": {"label": "3", "d1": 31700, "d2": 144, "d3": 0.00417, "output": 293.25387}, "129": {"label": "3", "d1": 53800, "d2": 72, "d3": 0.00083, "output": 770.08155}, "130": {"label": "3", "d1": 17200, "d2": 276, "d3": 0.005, "output": 115.04172}, "131": {"label": "3", "d1": 2500, "d2": 168, "d3": 0.00583, "output": 23.37951}, "132": {"label": "3", "d1": 97600, "d2": 72, "d3": 0.0025, "output": 1482.90276}, "133": {"label": "3", "d1": 98100, "d2": 144, "d3": 0.00417, "output": 907.51436}, "134": {"label": "3", "d1": 82100, "d2": 156, "d3": 0.00667, "output": 848.33695}, "135": {"label": "3", "d1": 53200, "d2": 348, "d3": 0.0075, "output": 431.00384}, "136": {"label": "3", "d1": 56000, "d2": 12, "d3": 0.00417, "output": 4794.12163}, "137": {"label": "3", "d1": 28100, "d2": 168, "d3": 0.0025, "output": 205.04441}, "138": {"label": "3", "d1": 46800, "d2": 24, "d3": 0.00083, "output": 1970.29559}, "139": {"label": "3", "d1": 75800, "d2": 312, "d3": 0.0025, "output": 350.18174}, "140": {"label": "3", "d1": 67500, "d2": 120, "d3": 0.00417, "output": 716.07421}, "141": {"label": "3", "d1": 55300, "d2": 144, "d3": 0.00667, "output": 598.71757}, "142": {"label": "3", "d1": 4100, "d2": 300, "d3": 0.00083, "output": 15.44435}, "143": {"label": "3", "d1": 18400, "d2": 108, "d3": 0.00167, "output": 186.3378}, "144": {"label": "3", "d1": 89800, "d2": 192, "d3": 0.0075, "output": 884.09523}, "145": {"label": "3", "d1": 45400, "d2": 276, "d3": 0.0025, "output": 227.91537}, "146": {"label": "3", "d1": 68800, "d2": 144, "d3": 0.005, "output": 671.38495}, "147": {"label": "3", "d1": 85500, "d2": 48, "d3": 0.00083, "output": 1817.70712}, "148": {"label": "3", "d1": 72600, "d2": 84, "d3": 0.0075, "output": 1168.06708}, "149": {"label": "3", "d1": 40900, "d2": 240, "d3": 0.0025, "output": 226.83042}, "150": {"label": "3", "d1": 50800, "d2": 156, "d3": 0.00083, "output": 347.31278}, "151": {"label": "3", "d1": 43400, "d2": 120, "d3": 0.00333, "output": 439.3214}, "152": {"label": "3", "d1": 79100, "d2": 180, "d3": 0.005, "output": 667.49075}, "153": {"label": "3", "d1": 2300, "d2": 180, "d3": 0.00417, "output": 18.19305}, "154": {"label": "3", "d1": 28700, "d2": 132, "d3": 0.00583, "output": 312.31352}, "155": {"label": "3", "d1": 33100, "d2": 36, "d3": 0.00333, "output": 977.18501}, "156": {"label": "3", "d1": 83500, "d2": 204, "d3": 0.00583, "output": 700.9243}, "157": {"label": "3", "d1": 62200, "d2": 240, "d3": 0.005, "output": 445.62012}, "158": {"label": "3", "d1": 47800, "d2": 240, "d3": 0.00667, "output": 399.93736}, "159": {"label": "3", "d1": 4800, "d2": 180, "d3": 0.00667, "output": 45.88238}, "160": {"label": "3", "d1": 26200, "d2": 204, "d3": 0.00667, "output": 235.40574}, "161": {"label": "3", "d1": 42600, "d2": 132, "d3": 0.00667, "output": 486.38979}, "162": {"label": "3", "d1": 52000, "d2": 312, "d3": 0.0075, "output": 431.97616}, "163": {"label": "3", "d1": 81800, "d2": 288, "d3": 0.0075, "output": 694.20742}, "164": {"label": "3", "d1": 7100, "d2": 312, "d3": 0.00333, "output": 36.62366}, "165": {"label": "3", "d1": 35800, "d2": 192, "d3": 0.00083, "output": 201.78697}, "166": {"label": "3", "d1": 46700, "d2": 240, "d3": 0.00667, "output": 390.73378}, "167": {"label": "3", "d1": 62100, "d2": 348, "d3": 0.0075, "output": 503.10786}, "168": {"label": "3", "d1": 13600, "d2": 60, "d3": 0.0025, "output": 244.37419}, "169": {"label": "3", "d1": 21600, "d2": 348, "d3": 0.0075, "output": 174.99404}, "170": {"label": "3", "d1": 67400, "d2": 24, "d3": 0.0075, "output": 3079.15163}, "171": {"label": "3", "d1": 49900, "d2": 96, "d3": 0.0075, "output": 731.04514}, "172": {"label": "3", "d1": 21400, "d2": 120, "d3": 0.00583, "output": 248.42803}, "173": {"label": "3", "d1": 67400, "d2": 144, "d3": 0.00583, "output": 692.98515}, "174": {"label": "3", "d1": 56900, "d2": 12, "d3": 0.005, "output": 4897.17985}, "175": {"label": "3", "d1": 39200, "d2": 144, "d3": 0.00167, "output": 306.49101}, "176": {"label": "3", "d1": 17700, "d2": 276, "d3": 0.00333, "output": 98.15245}, "177": {"label": "3", "d1": 41900, "d2": 120, "d3": 0.005, "output": 465.1759}, "178": {"label": "3", "d1": 77500, "d2": 120, "d3": 0.0025, "output": 748.34577}, "179": {"label": "3", "d1": 79300, "d2": 108, "d3": 0.005, "output": 952.05595}, "180": {"label": "3", "d1": 68000, "d2": 252, "d3": 0.00667, "output": 558.0626}, "181": {"label": "3", "d1": 66200, "d2": 36, "d3": 0.0075, "output": 2105.1423}, "182": {"label": "3", "d1": 58000, "d2": 276, "d3": 0.005, "output": 387.93138}, "183": {"label": "3", "d1": 57100, "d2": 204, "d3": 0.00167, "output": 330.51383}, "184": {"label": "3", "d1": 7400, "d2": 288, "d3": 0.00083, "output": 28.89829}, "185": {"label": "3", "d1": 60000, "d2": 36, "d3": 0.00667, "output": 1880.29265}, "186": {"label": "3", "d1": 90100, "d2": 264, "d3": 0.00333, "output": 513.53956}, "187": {"label": "3", "d1": 47900, "d2": 336, "d3": 0.00583, "output": 325.40634}, "188": {"label": "3", "d1": 55700, "d2": 72, "d3": 0.00333, "output": 871.33519}, "189": {"label": "3", "d1": 77700, "d2": 288, "d3": 0.00083, "output": 303.43202}, "190": {"label": "3", "d1": 18400, "d2": 108, "d3": 0.005, "output": 220.90579}, "191": {"label": "3", "d1": 43000, "d2": 324, "d3": 0.00333, "output": 217.14286}, "192": {"label": "3", "d1": 12900, "d2": 300, "d3": 0.00417, "output": 75.44218}, "193": {"label": "3", "d1": 26900, "d2": 168, "d3": 0.0025, "output": 196.28806}, "194": {"label": "3", "d1": 24200, "d2": 36, "d3": 0.005, "output": 736.21089}, "195": {"label": "3", "d1": 36300, "d2": 12, "d3": 0.00667, "output": 3157.74711}, "196": {"label": "3", "d1": 99400, "d2": 132, "d3": 0.0075, "output": 1188.90391}, "197": {"label": "3", "d1": 8900, "d2": 276, "d3": 0.00583, "output": 64.94062}, "198": {"label": "3", "d1": 97000, "d2": 108, "d3": 0.00083, "output": 939.37691}, "199": {"label": "3", "d1": 17400, "d2": 300, "d3": 0.00667, "output": 134.34213}, "200": {"label": "3", "d1": 19100, "d2": 348, "d3": 0.00667, "output": 141.38242}, "201": {"label": "2", "d1": 96000, "d2": 1300.11923, "d3": 0.0075, "output": 108}, "202": {"label": "2", "d1": 52500, "d2": 471.70998, "d3": 0.00667, "output": 204}, "203": {"label": "2", "d1": 41200, "d2": 483.25836, "d3": 0.0025, "output": 96}, "204": {"label": "2", "d1": 56400, "d2": 720.18284, "d3": 0.00167, "output": 84}, "205": {"label": "2", "d1": 90100, "d2": 833.50707, "d3": 0.00417, "output": 144}, "206": {"label": "2", "d1": 81700, "d2": 1579.48988, "d3": 0.005, "output": 60}, "207": {"label": "2", "d1": 9200, "d2": 416.10787, "d3": 0.00667, "output": 24}, "208": {"label": "2", "d1": 55400, "d2": 1586.8956, "d3": 0.00167, "output": 36}, "209": {"label": "2", "d1": 69500, "d2": 575.31175, "d3": 0.0025, "output": 144}, "210": {"label": "2", "d1": 31700, "d2": 276.82436, "d3": 0.00417, "output": 156}, "211": {"label": "2", "d1": 46100, "d2": 499.11175, "d3": 0.00667, "output": 144}, "212": {"label": "2", "d1": 24900, "d2": 204.95822, "d3": 0.0075, "output": 324}, "213": {"label": "2", "d1": 45400, "d2": 481.62621, "d3": 0.00417, "output": 120}, "214": {"label": "2", "d1": 88500, "d2": 1466.70058, "d3": 0.005, "output": 72}, "215": {"label": "2", "d1": 48700, "d2": 560.98518, "d3": 0.00417, "output": 108}, "216": {"label": "2", "d1": 42000, "d2": 619.59233, "d3": 0.00167, "output": 72}, "217": {"label": "2", "d1": 73300, "d2": 438.56755, "d3": 0.00083, "output": 180}, "218": {"label": "2", "d1": 26000, "d2": 141.72667, "d3": 0.00417, "output": 348}, "219": {"label": "2", "d1": 67900, "d2": 297.18082, "d3": 0.00167, "output": 288}, "220": {"label": "2", "d1": 69900, "d2": 547.38744, "d3": 0.005, "output": 204}, "221": {"label": "2", "d1": 31600, "d2": 163.655, "d3": 0.0025, "output": 264}, "222": {"label": "2", "d1": 81100, "d2": 324.30833, "d3": 0.00167, "output": 324}, "223": {"label": "2", "d1": 77100, "d2": 562.59515, "d3": 0.0025, "output": 168}, "224": {"label": "2", "d1": 57000, "d2": 1734.05043, "d3": 0.005, "output": 36}, "225": {"label": "2", "d1": 33500, "d2": 424.17112, "d3": 0.00417, "output": 96}, "226": {"label": "2", "d1": 71300, "d2": 302.34701, "d3": 0.00167, "output": 300}, "227": {"label": "2", "d1": 36200, "d2": 237.46406, "d3": 0.005, "output": 288}, "228": {"label": "2", "d1": 54500, "d2": 448.49133, "d3": 0.00333, "output": 156}, "229": {"label": "2", "d1": 1300, "d2": 6.86068, "d3": 0.00167, "output": 228}, "230": {"label": "2", "d1": 58200, "d2": 424.66789, "d3": 0.00583, "output": 276}, "231": {"label": "2", "d1": 74800, "d2": 1057.57569, "d3": 0.00667, "output": 96}, "232": {"label": "2", "d1": 95200, "d2": 8106.0969, "d3": 0.00333, "output": 12}, "233": {"label": "2", "d1": 10100, "d2": 61.30747, "d3": 0.005, "output": 348}, "234": {"label": "2", "d1": 46100, "d2": 1340.64376, "d3": 0.0025, "output": 36}, "235": {"label": "2", "d1": 97100, "d2": 1702.66732, "d3": 0.00667, "output": 72}, "236": {"label": "2", "d1": 40800, "d2": 319.00085, "d3": 0.00167, "output": 144}, "237": {"label": "2", "d1": 66900, "d2": 3025.82785, "d3": 0.00667, "output": 24}, "238": {"label": "2", "d1": 11400, "d2": 104.91576, "d3": 0.00167, "output": 120}, "239": {"label": "2", "d1": 84800, "d2": 618.76009, "d3": 0.00583, "output": 276}, "240": {"label": "2", "d1": 55000, "d2": 2388.2728, "d3": 0.00333, "output": 24}, "241": {"label": "2", "d1": 57000, "d2": 391.90589, "d3": 0.00583, "output": 324}, "242": {"label": "2", "d1": 74100, "d2": 304.91628, "d3": 0.00167, "output": 312}, "243": {"label": "2", "d1": 24500, "d2": 226.66413, "d3": 0.00667, "output": 192}, "244": {"label": "2", "d1": 89100, "d2": 493.44824, "d3": 0.00417, "output": 336}, "245": {"label": "2", "d1": 3400, "d2": 22.7408, "d3": 0.005, "output": 276}, "246": {"label": "2", "d1": 76400, "d2": 827.16135, "d3": 0.00667, "output": 144}, "247": {"label": "2", "d1": 14100, "d2": 107.56411, "d3": 0.00667, "output": 312}, "248": {"label": "2", "d1": 73500, "d2": 440.79662, "d3": 0.0025, "output": 216}, "249": {"label": "2", "d1": 29600, "d2": 655.17608, "d3": 0.0025, "output": 48}, "250": {"label": "2", "d1": 72900, "d2": 562.84721, "d3": 0.00667, "output": 300}, "251": {"label": "2", "d1": 61600, "d2": 1134.34657, "d3": 0.00333, "output": 60}, "252": {"label": "2", "d1": 94400, "d2": 7952.32056, "d3": 0.00167, "output": 12}, "253": {"label": "2", "d1": 13900, "d2": 243.66019, "d3": 0.00167, "output": 60}, "254": {"label": "2", "d1": 26400, "d2": 2296.54335, "d3": 0.00667, "output": 12}, "255": {"label": "2", "d1": 11700, "d2": 264.154, "d3": 0.00333, "output": 48}, "256": {"label": "2", "d1": 11000, "d2": 85.25647, "d3": 0.00583, "output": 240}, "257": {"label": "2", "d1": 32900, "d2": 165.16334, "d3": 0.0025, "output": 276}, "258": {"label": "2", "d1": 31900, "d2": 456.60969, "d3": 0.00083, "output": 72}, "259": {"label": "2", "d1": 95700, "d2": 1015.2341, "d3": 0.00417, "output": 120}, "260": {"label": "2", "d1": 60100, "d2": 422.65316, "d3": 0.00417, "output": 216}, "261": {"label": "2", "d1": 14700, "d2": 119.84447, "d3": 0.00583, "output": 216}, "262": {"label": "2", "d1": 24900, "d2": 256.0138, "d3": 0.00583, "output": 144}, "263": {"label": "2", "d1": 36400, "d2": 213.65572, "d3": 0.00333, "output": 252}, "264": {"label": "2", "d1": 52400, "d2": 313.51896, "d3": 0.00083, "output": 180}, "265": {"label": "2", "d1": 77300, "d2": 1745.22256, "d3": 0.00333, "output": 48}, "266": {"label": "2", "d1": 67100, "d2": 1426.52804, "d3": 0.00083, "output": 48}, "267": {"label": "2", "d1": 39700, "d2": 326.78078, "d3": 0.0075, "output": 324}, "268": {"label": "2", "d1": 6000, "d2": 38.27693, "d3": 0.00083, "output": 168}, "269": {"label": "2", "d1": 61300, "d2": 877.43492, "d3": 0.00083, "output": 72}, "270": {"label": "2", "d1": 47600, "d2": 314.24412, "d3": 0.00417, "output": 240}, "271": {"label": "2", "d1": 45100, "d2": 456.73014, "d3": 0.00167, "output": 108}, "272": {"label": "2", "d1": 55600, "d2": 704.3173, "d3": 0.0075, "output": 120}, "273": {"label": "2", "d1": 18300, "d2": 157.24607, "d3": 0.0075, "output": 276}, "274": {"label": "2", "d1": 70600, "d2": 746.73199, "d3": 0.0025, "output": 108}, "275": {"label": "2", "d1": 49100, "d2": 2132.07626, "d3": 0.00333, "output": 24}, "276": {"label": "2", "d1": 33800, "d2": 216.97643, "d3": 0.00417, "output": 252}, "277": {"label": "2", "d1": 54500, "d2": 1633.51177, "d3": 0.00417, "output": 36}, "278": {"label": "2", "d1": 95400, "d2": 649.19343, "d3": 0.00417, "output": 228}, "279": {"label": "2", "d1": 31900, "d2": 249.55883, "d3": 0.00667, "output": 288}, "280": {"label": "2", "d1": 28300, "d2": 873.77009, "d3": 0.00583, "output": 36}, "281": {"label": "2", "d1": 68300, "d2": 1257.72517, "d3": 0.00333, "output": 60}, "282": {"label": "2", "d1": 51100, "d2": 288.02554, "d3": 0.00083, "output": 192}, "283": {"label": "2", "d1": 75200, "d2": 695.7201, "d3": 0.00667, "output": 192}, "284": {"label": "2", "d1": 43800, "d2": 262.06355, "d3": 0.00083, "output": 180}, "285": {"label": "2", "d1": 9100, "d2": 44.36339, "d3": 0.0025, "output": 288}, "286": {"label": "2", "d1": 42800, "d2": 421.37278, "d3": 0.0075, "output": 192}, "287": {"label": "2", "d1": 42700, "d2": 354.71888, "d3": 0.0075, "output": 312}, "288": {"label": "2", "d1": 34700, "d2": 363.98131, "d3": 0.0075, "output": 168}, "289": {"label": "2", "d1": 33400, "d2": 1016.09271, "d3": 0.005, "output": 36}, "290": {"label": "2", "d1": 93300, "d2": 978.65869, "d3": 0.0075, "output": 168}, "291": {"label": "2", "d1": 31700, "d2": 1433.76297, "d3": 0.00667, "output": 24}, "292": {"label": "2", "d1": 44400, "d2": 266.27714, "d3": 0.0025, "output": 216}, "293": {"label": "2", "d1": 27300, "d2": 224.71323, "d3": 0.0075, "output": 324}, "294": {"label": "2", "d1": 39500, "d2": 173.90563, "d3": 0.0025, "output": 336}, "295": {"label": "2", "d1": 74300, "d2": 6259.08281, "d3": 0.00167, "output": 12}, "296": {"label": "2", "d1": 36600, "d2": 155.20197, "d3": 0.00167, "output": 300}, "297": {"label": "2", "d1": 11200, "d2": 165.22462, "d3": 0.00167, "output": 72}, "298": {"label": "2", "d1": 63200, "d2": 567.91814, "d3": 0.00583, "output": 180}, "299": {"label": "2", "d1": 66900, "d2": 376.83213, "d3": 0.00417, "output": 324}, "300": {"label": "2", "d1": 2900, "d2": 29.96562, "d3": 0.00667, "output": 156}, "301": {"label": "4", "d1": 66900, "d2": 48, "d3": 1633.35012, "output": 0.00667}, "302": {"label": "4", "d1": 67200, "d2": 228, "d3": 457.29348, "output": 0.00417}, "303": {"label": "4", "d1": 54200, "d2": 192, "d3": 533.60759, "output": 0.0075}, "304": {"label": "4", "d1": 83800, "d2": 240, "d3": 649.49932, "output": 0.00583}, "305": {"label": "4", "d1": 3000, "d2": 252, "d3": 26.53743, "output": 0.0075}, "306": {"label": "4", "d1": 40100, "d2": 300, "d3": 190.15874, "output": 0.0025}, "307": {"label": "4", "d1": 53000, "d2": 288, "d3": 449.79209, "output": 0.0075}, "308": {"label": "4", "d1": 93600, "d2": 228, "d3": 450.76456, "output": 0.00083}, "309": {"label": "4", "d1": 99600, "d2": 192, "d3": 702.97051, "output": 0.00333}, "310": {"label": "4", "d1": 15100, "d2": 204, "d3": 94.58258, "output": 0.0025}, "311": {"label": "4", "d1": 66000, "d2": 240, "d3": 435.71664, "output": 0.00417}, "312": {"label": "4", "d1": 67900, "d2": 24, "d3": 2888.60327, "output": 0.00167}, "313": {"label": "4", "d1": 46100, "d2": 180, "d3": 275.82488, "output": 0.00083}, "314": {"label": "4", "d1": 52900, "d2": 24, "d3": 2416.72287, "output": 0.0075}, "315": {"label": "4", "d1": 57000, "d2": 60, "d3": 1024.21537, "output": 0.0025}, "316": {"label": "4", "d1": 17800, "d2": 132, "d3": 212.90231, "output": 0.0075}, "317": {"label": "4", "d1": 6300, "d2": 120, "d3": 66.83359, "output": 0.00417}, "318": {"label": "4", "d1": 54300, "d2": 348, "d3": 179.71659, "output": 0.00083}, "319": {"label": "4", "d1": 26500, "d2": 132, "d3": 212.03907, "output": 0.00083}, "320": {"label": "4", "d1": 58800, "d2": 204, "d3": 340.354, "output": 0.00167}, "321": {"label": "4", "d1": 19600, "d2": 288, "d3": 140.63143, "output": 0.00583}, "322": {"label": "4", "d1": 51200, "d2": 168, "d3": 451.19279, "output": 0.005}, "323": {"label": "4", "d1": 80300, "d2": 324, "d3": 321.10924, "output": 0.00167}, "324": {"label": "4", "d1": 37900, "d2": 48, "d3": 872.8789, "output": 0.00417}, "325": {"label": "4", "d1": 91600, "d2": 24, "d3": 3937.07902, "output": 0.0025}, "326": {"label": "4", "d1": 36400, "d2": 48, "d3": 821.81244, "output": 0.00333}, "327": {"label": "4", "d1": 35600, "d2": 156, "d3": 310.88161, "output": 0.00417}, "328": {"label": "4", "d1": 17000, "d2": 48, "d3": 376.28356, "output": 0.0025}, "329": {"label": "4", "d1": 6200, "d2": 156, "d3": 51.02103, "output": 0.00333}, "330": {"label": "4", "d1": 63400, "d2": 192, "d3": 480.50349, "output": 0.00417}, "331": {"label": "4", "d1": 87900, "d2": 228, "d3": 423.31416, "output": 0.00083}, "332": {"label": "4", "d1": 73000, "d2": 84, "d3": 997.68846, "output": 0.00333}, "333": {"label": "4", "d1": 11000, "d2": 96, "d3": 139.28007, "output": 0.00417}, "334": {"label": "4", "d1": 42500, "d2": 48, "d3": 903.53863, "output": 0.00083}, "335": {"label": "4", "d1": 20300, "d2": 312, "d3": 128.63643, "output": 0.005}, "336": {"label": "4", "d1": 91200, "d2": 348, "d3": 553.58821, "output": 0.005}, "337": {"label": "4", "d1": 40900, "d2": 240, "d3": 247.75976, "output": 0.00333}, "338": {"label": "4", "d1": 77600, "d2": 252, "d3": 588.38531, "output": 0.00583}, "339": {"label": "4", "d1": 43200, "d2": 252, "d3": 301.90619, "output": 0.005}, "340": {"label": "4", "d1": 55000, "d2": 132, "d3": 598.51022, "output": 0.00583}, "341": {"label": "4", "d1": 96300, "d2": 264, "d3": 602.3629, "output": 0.00417}, "342": {"label": "4", "d1": 56500, "d2": 12, "d3": 4888.65697, "output": 0.00583}, "343": {"label": "4", "d1": 90800, "d2": 60, "d3": 1841.27043, "output": 0.00667}, "344": {"label": "4", "d1": 87500, "d2": 156, "d3": 953.47045, "output": 0.0075}, "345": {"label": "4", "d1": 41700, "d2": 300, "d3": 243.87124, "output": 0.00417}, "346": {"label": "4", "d1": 14200, "d2": 312, "d3": 73.24732, "output": 0.00333}, "347": {"label": "4", "d1": 10100, "d2": 192, "d3": 81.95522, "output": 0.005}, "348": {"label": "4", "d1": 46600, "d2": 348, "d3": 226.35708, "output": 0.00333}, "349": {"label": "4", "d1": 13100, "d2": 312, "d3": 67.57323, "output": 0.00333}, "350": {"label": "4", "d1": 92700, "d2": 12, "d3": 8020.85843, "output": 0.00583}, "351": {"label": "4", "d1": 55400, "d2": 108, "d3": 721.35167, "output": 0.00667}, "352": {"label": "4", "d1": 71100, "d2": 132, "d3": 568.90482, "output": 0.00083}, "353": {"label": "4", "d1": 18500, "d2": 84, "d3": 279.17841, "output": 0.00583}, "354": {"label": "4", "d1": 81300, "d2": 240, "d3": 731.4772, "output": 0.0075}, "355": {"label": "4", "d1": 27200, "d2": 324, "d3": 137.35549, "output": 0.00333}, "356": {"label": "4", "d1": 39900, "d2": 288, "d3": 338.61707, "output": 0.0075}, "357": {"label": "4", "d1": 13900, "d2": 300, "d3": 52.36011, "output": 0.00083}, "358": {"label": "4", "d1": 35100, "d2": 120, "d3": 338.92821, "output": 0.0025}, "359": {"label": "4", "d1": 16300, "d2": 192, "d3": 99.3027, "output": 0.00167}, "360": {"label": "4", "d1": 51900, "d2": 84, "d3": 783.20861, "output": 0.00583}, "361": {"label": "4", "d1": 91100, "d2": 336, "d3": 310.8042, "output": 0.00083}, "362": {"label": "4", "d1": 63000, "d2": 180, "d3": 602.2063, "output": 0.00667}, "363": {"label": "4", "d1": 58100, "d2": 288, "d3": 254.28874, "output": 0.00167}, "364": {"label": "4", "d1": 59100, "d2": 24, "d3": 2645.95226, "output": 0.00583}, "365": {"label": "4", "d1": 40200, "d2": 168, "d3": 274.6187, "output": 0.00167}, "366": {"label": "4", "d1": 73900, "d2": 180, "d3": 623.6102, "output": 0.005}, "367": {"label": "4", "d1": 92700, "d2": 180, "d3": 554.64136, "output": 0.00083}, "368": {"label": "4", "d1": 25700, "d2": 108, "d3": 283.70457, "output": 0.00333}, "369": {"label": "4", "d1": 94800, "d2": 312, "d3": 437.95817, "output": 0.0025}, "370": {"label": "4", "d1": 47100, "d2": 108, "d3": 565.47081, "output": 0.005}, "371": {"label": "4", "d1": 33800, "d2": 192, "d3": 293.03958, "output": 0.00583}, "372": {"label": "4", "d1": 80600, "d2": 312, "d3": 372.35684, "output": 0.0025}, "373": {"label": "4", "d1": 25500, "d2": 228, "d3": 159.7987, "output": 0.00333}, "374": {"label": "4", "d1": 92100, "d2": 276, "d3": 416.75975, "output": 0.00167}, "375": {"label": "4", "d1": 50700, "d2": 96, "d3": 716.83272, "output": 0.00667}, "376": {"label": "4", "d1": 84600, "d2": 240, "d3": 388.91963, "output": 0.00083}, "377": {"label": "4", "d1": 50300, "d2": 228, "d3": 342.28962, "output": 0.00417}, "378": {"label": "4", "d1": 28600, "d2": 48, "d3": 671.67183, "output": 0.005}, "379": {"label": "4", "d1": 36500, "d2": 204, "d3": 228.62677, "output": 0.0025}, "380": {"label": "4", "d1": 26400, "d2": 108, "d3": 279.23123, "output": 0.0025}, "381": {"label": "4", "d1": 28400, "d2": 348, "d3": 230.08476, "output": 0.0075}, "382": {"label": "4", "d1": 94700, "d2": 60, "d3": 1743.8737, "output": 0.00333}, "383": {"label": "4", "d1": 30100, "d2": 132, "d3": 312.04774, "output": 0.005}, "384": {"label": "4", "d1": 49500, "d2": 48, "d3": 1073.99504, "output": 0.00167}, "385": {"label": "4", "d1": 85100, "d2": 348, "d3": 689.44411, "output": 0.0075}, "386": {"label": "4", "d1": 8000, "d2": 204, "d3": 50.10998, "output": 0.0025}, "387": {"label": "4", "d1": 40800, "d2": 216, "d3": 244.6871, "output": 0.0025}, "388": {"label": "4", "d1": 73300, "d2": 240, "d3": 406.52004, "output": 0.0025}, "389": {"label": "4", "d1": 25800, "d2": 240, "d3": 199.96518, "output": 0.00583}, "390": {"label": "4", "d1": 78600, "d2": 60, "d3": 1483.42301, "output": 0.00417}, "391": {"label": "4", "d1": 93100, "d2": 264, "d3": 482.16078, "output": 0.0025}, "392": {"label": "4", "d1": 46500, "d2": 264, "d3": 240.82144, "output": 0.0025}, "393": {"label": "4", "d1": 66200, "d2": 24, "d3": 2787.04206, "output": 0.00083}, "394": {"label": "4", "d1": 71900, "d2": 132, "d3": 640.1806, "output": 0.0025}, "395": {"label": "4", "d1": 36700, "d2": 228, "d3": 176.74209, "output": 0.00083}, "396": {"label": "4", "d1": 25500, "d2": 132, "d3": 239.05614, "output": 0.00333}, "397": {"label": "4", "d1": 61000, "d2": 60, "d3": 1207.75799, "output": 0.00583}, "398": {"label": "4", "d1": 32800, "d2": 84, "d3": 448.27646, "output": 0.00333}, "399": {"label": "4", "d1": 42600, "d2": 144, "d3": 461.21824, "output": 0.00667}, "400": {"label": "4", "d1": 9200, "d2": 24, "d3": 411.89104, "output": 0.00583}}